{
	"credit": "Made by XeKr with Blockbench",
	"parent": "minecraft:block/template_wall_post",
	"render_type": "minecraft:cutout",
	"textures": {
		"1": "anvilcraft:block/heavy_iron_wall",
		"wall": "anvilcraft:block/heavy_iron_wall_post",
		"particle": "anvilcraft:block/heavy_iron_wall"
	},
	"elements": [
		{
			"from": [4, 0, 4],
			"to": [12, 16, 12],
			"faces": {
				"north": {"uv": [4, 0, 12, 16], "texture": "#wall"},
				"east": {"uv": [4, 0, 12, 16], "texture": "#wall"},
				"south": {"uv": [4, 0, 12, 16], "texture": "#wall"},
				"west": {"uv": [4, 0, 12, 16], "texture": "#wall"},
				"up": {"uv": [4, 4, 12, 12], "texture": "#1"},
				"down": {"uv": [4, 4, 12, 12], "texture": "#1"}
			}
		}
	]
}